sensirion_i2c_adapter/__init__.py
sensirion_i2c_adapter/channel.py
sensirion_i2c_adapter/i2c_channel.py
sensirion_i2c_adapter/multi_channel.py
sensirion_i2c_adapter/multi_device_support.py
sensirion_i2c_adapter/multi_sensor_bridge.py
sensirion_i2c_adapter/transfer.py
sensirion_i2c_adapter/version.py
sensirion_i2c_adapter-1.2.0.dist-info/LICENSE
sensirion_i2c_adapter-1.2.0.dist-info/METADATA
sensirion_i2c_adapter-1.2.0.dist-info/WHEEL
sensirion_i2c_adapter-1.2.0.dist-info/top_level.txt
sensirion_i2c_adapter-1.2.0.dist-info/RECORD
